topsis/__init__.py
topsis/__main__.py
topsis_drishti_102117158-1.0.2.dist-info/METADATA
topsis_drishti_102117158-1.0.2.dist-info/WHEEL
topsis_drishti_102117158-1.0.2.dist-info/entry_points.txt
topsis_drishti_102117158-1.0.2.dist-info/top_level.txt
topsis_drishti_102117158-1.0.2.dist-info/RECORD
